skoleintra/__init__.py
skoleintra-0.0.4.dist-info/LICENSE
skoleintra-0.0.4.dist-info/METADATA
skoleintra-0.0.4.dist-info/WHEEL
skoleintra-0.0.4.dist-info/top_level.txt
skoleintra-0.0.4.dist-info/RECORD
