Metadata-Version: 2.1
Name: skoleintra
Version: 0.0.4
Summary: Benyt ItsLearnings skoleintra kun ved brug af Python
Home-page: https://github.com/jona799t/skoleintra-api
Author: jona799t
License: UNKNOWN
Keywords: python,skoleintra,elevintra
Platform: UNKNOWN
Classifier: Development Status :: 1 - Planning
Classifier: Intended Audience :: Developers
Classifier: Programming Language :: Python :: 3
Classifier: Operating System :: Unix
Classifier: Operating System :: MacOS :: MacOS X
Classifier: Operating System :: Microsoft :: Windows
Requires-Dist: bs4
Requires-Dist: httpx (==0.22.0)
Requires-Dist: requests
Requires-Dist: unilogin
